plugins/__init__.py
plugins/code1.py
plugins/httpget.py
plugins/httppost.py
xiaomusic-0.4.22.dist-info/METADATA
xiaomusic-0.4.22.dist-info/WHEEL
xiaomusic-0.4.22.dist-info/entry_points.txt
xiaomusic-0.4.22.dist-info/licenses/LICENSE
xiaomusic/__init__.py
xiaomusic/analytics.py
xiaomusic/api/__init__.py
xiaomusic/api/app.py
xiaomusic/api/dependencies.py
xiaomusic/api/models.py
xiaomusic/api/routers/__init__.py
xiaomusic/api/routers/device.py
xiaomusic/api/routers/file.py
xiaomusic/api/routers/music.py
xiaomusic/api/routers/playlist.py
xiaomusic/api/routers/plugin.py
xiaomusic/api/routers/system.py
xiaomusic/api/websocket.py
xiaomusic/auth.py
xiaomusic/cli.py
xiaomusic/command_handler.py
xiaomusic/config.py
xiaomusic/config_manager.py
xiaomusic/const.py
xiaomusic/conversation.py
xiaomusic/crontab.py
xiaomusic/device_manager.py
xiaomusic/device_player.py
xiaomusic/events.py
xiaomusic/file_watcher.py
xiaomusic/holiday.py
xiaomusic/js_adapter.py
xiaomusic/js_plugin_manager.py
xiaomusic/js_plugin_runner.js
xiaomusic/music_library.py
xiaomusic/online_music.py
xiaomusic/plugin.py
xiaomusic/plugins-config-example.json
xiaomusic/static/default/debug.html
xiaomusic/static/default/downloadtool.html
xiaomusic/static/default/favicon.ico
xiaomusic/static/default/index.html
xiaomusic/static/default/jquery-3.7.1.min.js
xiaomusic/static/default/m3u.html
xiaomusic/static/default/main.css
xiaomusic/static/default/materialicons.woff2
xiaomusic/static/default/materialiconsoutlined.woff2
xiaomusic/static/default/md.js
xiaomusic/static/default/merge/index.html
xiaomusic/static/default/merge/main.js
xiaomusic/static/default/merge/tailwind.css
xiaomusic/static/default/qrcode.png
xiaomusic/static/default/setting.css
xiaomusic/static/default/setting.html
xiaomusic/static/default/setting.js
xiaomusic/static/favicon.ico
xiaomusic/static/icons/android/android-launchericon-144-144.png
xiaomusic/static/icons/android/android-launchericon-192-192.png
xiaomusic/static/icons/android/android-launchericon-48-48.png
xiaomusic/static/icons/android/android-launchericon-512-512.png
xiaomusic/static/icons/android/android-launchericon-72-72.png
xiaomusic-0.4.22.dist-info/RECORD
