Metadata-Version: 2.1
Name: xiaomusic
Version: 0.4.22
Summary: Play Music with xiaomi AI speaker
Author-Email: =?utf-8?b?5ra15pum?= <im.hanxi@gmail.com>
License: MIT
Project-URL: Homepage, https://github.com/hanxi/xiaomusic
Requires-Python: >=3.10
Requires-Dist: aiohttp>=3.8.6
Requires-Dist: watchdog>=6.0.0
Requires-Dist: mutagen>=1.47.0
Requires-Dist: yt-dlp[default]>=2024.12.1.232904.dev0
Requires-Dist: uvicorn>=0.30.1
Requires-Dist: fastapi>=0.115.4
Requires-Dist: starlette>=0.37.2
Requires-Dist: aiofiles>=24.1.0
Requires-Dist: ga4mp>=2.0.4
Requires-Dist: apscheduler>=3.10.4
Requires-Dist: opencc-python-reimplemented==0.1.7
Requires-Dist: pillow>=10.4.0
Requires-Dist: python-multipart>=0.0.12
Requires-Dist: requests>=2.32.3
Requires-Dist: sentry-sdk[fastapi]==1.45.1
Requires-Dist: pyjwt>=2.10.1
Requires-Dist: fake-useragent>=2.2.0
Requires-Dist: miservice-fork
Requires-Dist: edge-tts>=7.2.3
Requires-Dist: psutil>=5.9.0
